{
	"version": "5",
	"dialect": "sqlite",
	"id": "08459dfc-1f78-424d-9459-2a208c9db619",
	"prevId": "815ceb55-4475-44c4-bb6f-1f0c5bc5e363",
	"tables": {
		"user": {
			"name": "user",
			"columns": {
				"id": {
					"name": "id",
					"type": "text",
					"primaryKey": true,
					"notNull": true,
					"autoincrement": false
				},
				"email": {
					"name": "email",
					"type": "text",
					"primaryKey": false,
					"notNull": true,
					"autoincrement": false
				},
				"username": {
					"name": "username",
					"type": "text",
					"primaryKey": false,
					"notNull": true,
					"autoincrement": false
				},
				"customer_id": {
					"name": "customer_id",
					"type": "text",
					"primaryKey": false,
					"notNull": false,
					"autoincrement": false
				},
				"ai_credits": {
					"name": "ai_credits",
					"type": "integer",
					"primaryKey": false,
					"notNull": false,
					"autoincrement": false,
					"default": 0
				},
				"key_hash": {
					"name": "key_hash",
					"type": "text",
					"primaryKey": false,
					"notNull": false,
					"autoincrement": false
				}
			},
			"indexes": {},
			"foreignKeys": {},
			"compositePrimaryKeys": {},
			"uniqueConstraints": {}
		},
		"user_article": {
			"name": "user_article",
			"columns": {
				"id": {
					"name": "id",
					"type": "integer",
					"primaryKey": true,
					"notNull": true,
					"autoincrement": true
				},
				"content": {
					"name": "content",
					"type": "text",
					"primaryKey": false,
					"notNull": true,
					"autoincrement": false
				},
				"title": {
					"name": "title",
					"type": "text",
					"primaryKey": false,
					"notNull": true,
					"autoincrement": false
				},
				"author": {
					"name": "author",
					"type": "text",
					"primaryKey": false,
					"notNull": true,
					"autoincrement": false
				}
			},
			"indexes": {},
			"foreignKeys": {
				"user_article_author_user_id_fk": {
					"name": "user_article_author_user_id_fk",
					"tableFrom": "user_article",
					"tableTo": "user",
					"columnsFrom": ["author"],
					"columnsTo": ["id"],
					"onDelete": "no action",
					"onUpdate": "no action"
				}
			},
			"compositePrimaryKeys": {},
			"uniqueConstraints": {}
		},
		"user_image": {
			"name": "user_image",
			"columns": {
				"id": {
					"name": "id",
					"type": "integer",
					"primaryKey": true,
					"notNull": true,
					"autoincrement": true
				},
				"url": {
					"name": "url",
					"type": "text",
					"primaryKey": false,
					"notNull": true,
					"autoincrement": false
				},
				"description": {
					"name": "description",
					"type": "text",
					"primaryKey": false,
					"notNull": true,
					"autoincrement": false,
					"default": "'no description provided, sorry'"
				},
				"user_id": {
					"name": "user_id",
					"type": "text",
					"primaryKey": false,
					"notNull": true,
					"autoincrement": false
				}
			},
			"indexes": {},
			"foreignKeys": {
				"user_image_user_id_user_id_fk": {
					"name": "user_image_user_id_user_id_fk",
					"tableFrom": "user_image",
					"tableTo": "user",
					"columnsFrom": ["user_id"],
					"columnsTo": ["id"],
					"onDelete": "no action",
					"onUpdate": "no action"
				}
			},
			"compositePrimaryKeys": {},
			"uniqueConstraints": {}
		},
		"user_key": {
			"name": "user_key",
			"columns": {
				"id": {
					"name": "id",
					"type": "text",
					"primaryKey": true,
					"notNull": true,
					"autoincrement": false
				},
				"user_id": {
					"name": "user_id",
					"type": "text",
					"primaryKey": false,
					"notNull": true,
					"autoincrement": false
				},
				"hashed_password": {
					"name": "hashed_password",
					"type": "text",
					"primaryKey": false,
					"notNull": false,
					"autoincrement": false
				}
			},
			"indexes": {},
			"foreignKeys": {
				"user_key_user_id_user_id_fk": {
					"name": "user_key_user_id_user_id_fk",
					"tableFrom": "user_key",
					"tableTo": "user",
					"columnsFrom": ["user_id"],
					"columnsTo": ["id"],
					"onDelete": "no action",
					"onUpdate": "no action"
				}
			},
			"compositePrimaryKeys": {},
			"uniqueConstraints": {}
		},
		"user_preference": {
			"name": "user_preference",
			"columns": {
				"id": {
					"name": "id",
					"type": "integer",
					"primaryKey": true,
					"notNull": true,
					"autoincrement": true
				},
				"key": {
					"name": "key",
					"type": "text",
					"primaryKey": false,
					"notNull": true,
					"autoincrement": false
				},
				"value": {
					"name": "value",
					"type": "text",
					"primaryKey": false,
					"notNull": true,
					"autoincrement": false
				}
			},
			"indexes": {
				"user_preference_key_unique": {
					"name": "user_preference_key_unique",
					"columns": ["key"],
					"isUnique": true
				}
			},
			"foreignKeys": {},
			"compositePrimaryKeys": {},
			"uniqueConstraints": {}
		},
		"user_session": {
			"name": "user_session",
			"columns": {
				"id": {
					"name": "id",
					"type": "text",
					"primaryKey": true,
					"notNull": true,
					"autoincrement": false
				},
				"user_id": {
					"name": "user_id",
					"type": "text",
					"primaryKey": false,
					"notNull": true,
					"autoincrement": false
				},
				"active_expires": {
					"name": "active_expires",
					"type": "integer",
					"primaryKey": false,
					"notNull": true,
					"autoincrement": false
				},
				"idle_expires": {
					"name": "idle_expires",
					"type": "integer",
					"primaryKey": false,
					"notNull": true,
					"autoincrement": false
				}
			},
			"indexes": {},
			"foreignKeys": {
				"user_session_user_id_user_id_fk": {
					"name": "user_session_user_id_user_id_fk",
					"tableFrom": "user_session",
					"tableTo": "user",
					"columnsFrom": ["user_id"],
					"columnsTo": ["id"],
					"onDelete": "no action",
					"onUpdate": "no action"
				}
			},
			"compositePrimaryKeys": {},
			"uniqueConstraints": {}
		}
	},
	"enums": {},
	"_meta": {
		"schemas": {},
		"tables": {},
		"columns": {}
	}
}
